README.md
setup.py
fladm/__init__.py
fladm/cli.py
fladm/flamingo-cli-config.json
fladm/get_pass.py
fladm/service.py
fladm/showlog.py
fladm/status.py
fladm/version.py
fladm.egg-info/PKG-INFO
fladm.egg-info/SOURCES.txt
fladm.egg-info/dependency_links.txt
fladm.egg-info/entry_points.txt
fladm.egg-info/not-zip-safe
fladm.egg-info/requires.txt
fladm.egg-info/top_level.txt
flcli/__init__.py
flcli/cli.py
flcli/fl3/__init__.py
flcli/fl3/abs.py
flcli/fl3/auth.py
flcli/fl3/hdfs.py
flcli/fl3/oozie.py
flcli/fl3/util.py