Metadata-Version: 1.1
Name: fladm
Version: 1.7.15
Summary: Flamingo admin cli tool
Home-page: http://gitlab.exem-oss.org/flamingo/flamingo-adm-cli.git
Author: Jaeik Park
Author-email: jaeikpark81@gmail.com
License: Apache2
Platform: UNKNOWN
Classifier: Programming Language :: Python :: 2.7
